download_water_data/__init__.py
download_water_data/__main__.py
download_water_data-0.5.0.dist-info/LICENSE
download_water_data-0.5.0.dist-info/METADATA
download_water_data-0.5.0.dist-info/WHEEL
download_water_data-0.5.0.dist-info/entry_points.txt
download_water_data-0.5.0.dist-info/top_level.txt
download_water_data-0.5.0.dist-info/RECORD
