Metadata-Version: 2.1
Name: download-water-data
Version: 0.5.0
Summary: Downloader for the Global Surface Water Data of the Copernicus Programme
Home-page: https://github.com/mentaljam/download_water_data
Author: Petr Tsymbarovich
Author-email: petr@tsymbarovich.ru
License: MIT
Keywords: Copernicus global surface water download
Classifier: Development Status :: 5 - Production/Stable
Classifier: Environment :: Console
Classifier: Intended Audience :: Science/Research
Classifier: License :: OSI Approved :: MIT License
Classifier: Natural Language :: English
Classifier: Operating System :: OS Independent
Classifier: Programming Language :: Python :: 2
Classifier: Programming Language :: Python :: 3
Classifier: Topic :: Scientific/Engineering :: GIS
License-File: LICENSE
